cinderclient/__init__.py
cinderclient/_i18n.py
cinderclient/api_versions.py
cinderclient/base.py
cinderclient/client.py
cinderclient/exceptions.py
cinderclient/extension.py
cinderclient/shell.py
cinderclient/shell_utils.py
cinderclient/utils.py
cinderclient/version.py
cinderclient/apiclient/__init__.py
cinderclient/apiclient/base.py
cinderclient/apiclient/exceptions.py
cinderclient/contrib/__init__.py
cinderclient/contrib/noauth.py
cinderclient/tests/__init__.py
cinderclient/tests/functional/__init__.py
cinderclient/tests/functional/base.py
cinderclient/tests/functional/test_cli.py
cinderclient/tests/functional/test_readonly_cli.py
cinderclient/tests/functional/test_snapshot_create_cli.py
cinderclient/tests/functional/test_volume_create_cli.py
cinderclient/tests/functional/test_volume_extend_cli.py
cinderclient/tests/unit/__init__.py
cinderclient/tests/unit/fake_actions_module.py
cinderclient/tests/unit/fakes.py
cinderclient/tests/unit/test_api_versions.py
cinderclient/tests/unit/test_auth_plugins.py
cinderclient/tests/unit/test_base.py
cinderclient/tests/unit/test_client.py
cinderclient/tests/unit/test_exceptions.py
cinderclient/tests/unit/test_http.py
cinderclient/tests/unit/test_shell.py
cinderclient/tests/unit/test_utils.py
cinderclient/tests/unit/utils.py
cinderclient/tests/unit/fixture_data/__init__.py
cinderclient/tests/unit/fixture_data/availability_zones.py
cinderclient/tests/unit/fixture_data/base.py
cinderclient/tests/unit/fixture_data/client.py
cinderclient/tests/unit/fixture_data/keystone_client.py
cinderclient/tests/unit/fixture_data/snapshots.py
cinderclient/tests/unit/v3/__init__.py
cinderclient/tests/unit/v3/fakes.py
cinderclient/tests/unit/v3/fakes_base.py
cinderclient/tests/unit/v3/test_attachments.py
cinderclient/tests/unit/v3/test_auth.py
cinderclient/tests/unit/v3/test_availability_zone.py
cinderclient/tests/unit/v3/test_capabilities.py
cinderclient/tests/unit/v3/test_cgsnapshots.py
cinderclient/tests/unit/v3/test_clusters.py
python_cinderclient-9.8.0.dist-info/AUTHORS
python_cinderclient-9.8.0.dist-info/LICENSE
python_cinderclient-9.8.0.dist-info/METADATA
python_cinderclient-9.8.0.dist-info/WHEEL
python_cinderclient-9.8.0.dist-info/entry_points.txt
python_cinderclient-9.8.0.dist-info/pbr.json
python_cinderclient-9.8.0.dist-info/top_level.txt
python_cinderclient-9.8.0.dist-info/RECORD
