Metadata-Version: 2.1
Name: python-cinderclient
Version: 9.8.0
Summary: OpenStack Block Storage API Client Library
Home-page: https://docs.openstack.org/python-cinderclient/latest/
Author: OpenStack
Author-email: openstack-discuss@lists.openstack.org
Classifier: Development Status :: 5 - Production/Stable
Classifier: Environment :: Console
Classifier: Environment :: OpenStack
Classifier: Intended Audience :: Information Technology
Classifier: Intended Audience :: System Administrators
Classifier: License :: OSI Approved :: Apache Software License
Classifier: Operating System :: POSIX :: Linux
Classifier: Programming Language :: Python
Classifier: Programming Language :: Python :: 3 :: Only
Classifier: Programming Language :: Python :: 3
Classifier: Programming Language :: Python :: 3.10
Classifier: Programming Language :: Python :: 3.11
Classifier: Programming Language :: Python :: 3.12
Requires-Python: >=3.10
License-File: LICENSE
Requires-Dist: pbr>=5.5.0
Requires-Dist: PrettyTable>=0.7.2
Requires-Dist: keystoneauth1>=5.9.0
Requires-Dist: oslo.i18n>=5.0.1
Requires-Dist: oslo.utils>=4.8.0
Requires-Dist: requests>=2.25.1
Requires-Dist: stevedore>=3.3.0
